accelapy/__init__.py
accelapy/authentication_client/__init__.py
accelapy/authentication_client/api/__init__.py
accelapy/authentication_client/api/default/__init__.py
accelapy/authentication_client/api/default/oauth2_authorize.py
accelapy/authentication_client/api/default/oauth2_token.py
accelapy/authentication_client/api/default/oauth2_tokeninfo.py
accelapy/authentication_client/client.py
accelapy/authentication_client/errors.py
accelapy/authentication_client/models/__init__.py
accelapy/authentication_client/models/request_authorize.py
accelapy/authentication_client/models/request_authorize_response_type.py
accelapy/authentication_client/models/request_token.py
accelapy/authentication_client/models/request_token_grant_type.py
accelapy/authentication_client/models/response_authorize.py
accelapy/authentication_client/models/response_error.py
accelapy/authentication_client/models/response_status.py
accelapy/authentication_client/models/response_token.py
accelapy/authentication_client/models/response_tokeninfo.py
accelapy/authentication_client/py.typed
accelapy/authentication_client/types.py
accelapy/client.py
accelapy/create_get_headers.py
accelapy/payload.py
accelapy/records_client/__init__.py
accelapy/records_client/api/__init__.py
accelapy/records_client/api/records/__init__.py
accelapy/records_client/api/records/v4_delete_records_ids.py
accelapy/records_client/api/records/v4_get_records.py
accelapy/records_client/api/records/v4_get_records_describe_create.py
accelapy/records_client/api/records/v4_get_records_ids.py
accelapy/records_client/api/records/v4_get_records_mine.py
accelapy/records_client/api/records/v4_post_records.py
accelapy/records_client/api/records/v4_put_records_id.py
accelapy/records_client/api/records/v_4_delete_records_record_id_related_child_record_ids.py
accelapy/records_client/api/records/v_4_get_records_record_id_additional.py
accelapy/records_client/api/records/v_4_get_records_record_id_related.py
accelapy-0.3.5.dist-info/METADATA
accelapy-0.3.5.dist-info/WHEEL
accelapy-0.3.5.dist-info/RECORD
