Metadata-Version: 2.4
Name: accelapy
Version: 0.3.5
Summary: Accela REST API
License: AGPL-3.0-or-later
Keywords: accela,rest,api
Author: MichaelAChrisco
Author-email: michaelachrisco@gmail.com
Requires-Python: >=3.10,<4.0
Classifier: License :: OSI Approved :: GNU Affero General Public License v3 or later (AGPLv3+)
Classifier: Programming Language :: Python :: 3
Classifier: Programming Language :: Python :: 3.10
Classifier: Programming Language :: Python :: 3.11
Classifier: Programming Language :: Python :: 3.12
Classifier: Programming Language :: Python :: 3.13
Classifier: Programming Language :: Python :: 3.14
Requires-Dist: attrs (>=24.2.0,<25.0.0)
Requires-Dist: httpx (>=0.27.2,<0.28.0)
Requires-Dist: python-dateutil (>=2.9.0.post0,<3.0.0)
Requires-Dist: requests (>=2.32.3,<3.0.0)
Project-URL: Homepage, https://github.com/michaelachrisco/accelapy
Project-URL: Repository, https://github.com/michaelachrisco/accelapy
